{
	"name": "DemoTrigger",
	"properties": {
		"description": "Daily trigger",
		"annotations": [],
		"runtimeState": "Started",
		"pipelines": [
			{
				"pipelineReference": {
					"referenceName": "pipeline1",
					"type": "PipelineReference"
				}
			}
		],
		"type": "ScheduleTrigger",
		"typeProperties": {
			"recurrence": {
				"frequency": "Day",
				"interval": 1,
				"startTime": "2025-02-06T11:06:00",
				"endTime": "2025-02-07T11:06:00",
				"timeZone": "India Standard Time",
				"schedule": {
					"minutes": [
						0
					],
					"hours": [
						10
					]
				}
			}
		}
	}
}